chaos_lambda.py
tests/__init__.py
tests/test_delay.py
tests/test_exception.py
tests/test_getconfig.py
tests/test_statuscode.py
chaos_lambda-0.3.dist-info/LICENSE
chaos_lambda-0.3.dist-info/METADATA
chaos_lambda-0.3.dist-info/WHEEL
chaos_lambda-0.3.dist-info/top_level.txt
chaos_lambda-0.3.dist-info/RECORD
