Metadata-Version: 2.1
Name: chaos-lambda
Version: 0.3
Summary: Decorators and Class to inject failures into AWS Lambda functions
Home-page: https://github.com/adhorn/aws-lambda-chaos-injection
Author: Adrian Hornsby
Author-email: hornsby.adrian@gmail.com
License: MIT
Keywords: chaos engineering lambda decorator aws lambda
Platform: UNKNOWN
Classifier: Development Status :: 3 - Alpha
Classifier: Intended Audience :: Developers
Classifier: License :: OSI Approved :: MIT License
Classifier: Programming Language :: Python :: 3
Classifier: Programming Language :: Python :: 3.6
Classifier: Programming Language :: Python :: 3.7
Classifier: Topic :: Software Development :: Libraries
Requires-Dist: boto3
Requires-Dist: future
Requires-Dist: ssm-cache
Requires-Dist: requests
